_hellchin_lib/__init__.py
_hellchin_lib/logger.py
_hellchin_lib/assertion/__init__.py
_hellchin_lib/assertion/base_soft_assert.py
_hellchin_lib/assertion/logger.py
_hellchin_lib/assertion/method_assert.py
_hellchin_lib/assertion/postman.py
hellchin_lib/__init__.py
tests/__init__.py
tests/test_soft_assert/__init__.py
tests/test_soft_assert/test_demo.py
tests/test_soft_assert/test_method_assert.py
tests/test_soft_assert/test_soft_assert.py
hellchin_lib-0.1.401.dist-info/LICENSE
hellchin_lib-0.1.401.dist-info/METADATA
hellchin_lib-0.1.401.dist-info/WHEEL
hellchin_lib-0.1.401.dist-info/top_level.txt
hellchin_lib-0.1.401.dist-info/RECORD
