Metadata-Version: 2.1
Name: hellchin_lib
Version: 0.1.401
Summary: A Python library for soft assertions and flexible testing.
Author: hellchin
Author-email: your.email@example.com
Classifier: Programming Language :: Python :: 3
Classifier: License :: OSI Approved :: MIT License
Classifier: Operating System :: OS Independent
License-File: LICENSE
Requires-Dist: pytest>=6.0.0
